hemopi2/Model/HemoPI2_reg.sav
hemopi2/Model/composition_calculate.py
hemopi2/Model/composition_calculate_hemopi2_2.py
hemopi2/Model/config.json
hemopi2/Model/hemopi2_ml_clf.sav
hemopi2/Model/pytorch_model.bin
hemopi2/Model/special_tokens_map.json
hemopi2/Model/tokenizer_config.json
hemopi2/Model/vocab.txt
hemopi2/Model/Data/AAIndexNames.csv
hemopi2/Model/Data/Grantham.csv
hemopi2/Model/Data/HemoPI2_reg.sav
hemopi2/Model/Data/PhysicoChemical.csv
hemopi2/Model/Data/Schneider-Wrede.csv
hemopi2/Model/Data/aa_attr_group.csv
hemopi2/Model/Data/aaind.txt
hemopi2/Model/Data/aaindex.csv
hemopi2/Model/Data/aaindices.csv
hemopi2/Model/Data/atom.csv
hemopi2/Model/Data/bin_di.csv
hemopi2/Model/Data/bonds.csv
hemopi2/Model/Data/can_pat.csv
hemopi2/Model/Data/data
hemopi2/Model/Data/example.fasta
hemopi2/Model/Data/z_aaindex.csv
hemopi2/merci/MERCI_motif_locator.pl
hemopi2/motif/all_neg.txt
hemopi2/motif/all_pos.txt
hemopi2/motif/neg_motif_1.txt
hemopi2/motif/neg_motif_2.txt
hemopi2/motif/pos_motif_1.txt
hemopi2/motif/pos_motif_2.txt
hemopi2/python_scripts/__init__.py
hemopi2/python_scripts/hemopi2_classification.py
hemopi2/python_scripts/hemopi2_regression.py
hemopi2-1.3.dist-info/LICENSE.txt
hemopi2-1.3.dist-info/METADATA
hemopi2-1.3.dist-info/WHEEL
hemopi2-1.3.dist-info/entry_points.txt
hemopi2-1.3.dist-info/top_level.txt
hemopi2-1.3.dist-info/RECORD
