Metadata-Version: 2.1
Name: hemopi2
Version: 1.3
Summary: HemoPI2.0: A tool to predict hemolytic activity of peptides.
Home-page: https://github.com/raghavagps/hemopi2
Author: Anand Singh Rathore
Author-email: anandr@iiitd.ac.in
License: LICENSE.txt
Requires-Python: >=3.6
License-File: LICENSE.txt
Requires-Dist: numpy
Requires-Dist: pandas
Requires-Dist: scikit-learn (==1.3.1)
Requires-Dist: transformers
